README.md
setup.py
cfgr/Context.py
cfgr/Instance.py
cfgr/Json.py
cfgr/Port.py
cfgr/PortBuilder.py
cfgr/PortTools.py
cfgr/Runtime.py
cfgr/Type.py
cfgr/TypeBuilder.py
cfgr/__init__.py
cfgr/app.py
cfgr/discover.py
cfgr/embeddedEvento.py
cfgr/event.py
cfgr/launch_on_startup.py
cfgr.egg-info/PKG-INFO
cfgr.egg-info/SOURCES.txt
cfgr.egg-info/dependency_links.txt
cfgr.egg-info/not-zip-safe
cfgr.egg-info/requires.txt
cfgr.egg-info/top_level.txt
cfgr/components/Cmd.py
cfgr/components/Event.py
cfgr/components/HttpFileHandler.py
cfgr/components/HttpScope.py
cfgr/components/HttpServer.py
cfgr/components/Interval.py
cfgr/components/LaunchOnStartup.py
cfgr/components/OscIn.py
cfgr/components/OscMessage.py
cfgr/components/OscOut.py
cfgr/components/Runner.py
cfgr/components/Thread.py
cfgr/components/__init__.py
cfgr/components/app.py
cfgr/components/bool.py
cfgr/components/int.py
cfgr/components/print.py
cfgr/components/string.py