Metadata-Version: 2.1
Name: cfgr
Version: 0.0.3
Summary: cfgr separates logic from data
Home-page: http://github.com/markkorput/pycfgr
Author: Short Notion
Author-email: shortnotion@gmail.com
License: MIT
Platform: UNKNOWN
